src/__main__.py
src/config.py
src/idle_tracker.py
src/sway_tracker.py
time_narrator-0.2.0.dist-info/licenses/LICENSE
time_narrator-0.2.0.dist-info/METADATA
time_narrator-0.2.0.dist-info/WHEEL
time_narrator-0.2.0.dist-info/entry_points.txt
time_narrator-0.2.0.dist-info/top_level.txt
time_narrator-0.2.0.dist-info/RECORD
