Metadata-Version: 2.4
Name: time-narrator
Version: 0.2.0
Summary: A background service that periodically narrates the time and your activity on Sway.
License: # GNU GENERAL PUBLIC LICENSE
Classifier: Programming Language :: Python :: 3
Classifier: License :: OSI Approved :: GNU General Public License v3 or later (GPLv3+)
Classifier: Operating System :: POSIX :: Linux
Classifier: Topic :: Desktop Environment
Requires-Python: >=3.11
License-File: LICENSE
Requires-Dist: i3ipc>=2.2.1
Requires-Dist: piper>=0.14.4
Requires-Dist: pywayland>=0.4.18
Dynamic: license-file
